heaume_cli/__init__.py
heaume_cli/commands/japscan/__init__.py
heaume_cli/commands/japscan/target.py
heaume_cli/commands/plant/__init__.py
heaume_cli/commands/plant/ls.py
heaume_cli/commands/plant/status.py
heaume_cli/utils/console.py
heaume_cli/utils/influxdb.py
heaume_cli-0.2.1.dist-info/entry_points.txt
heaume_cli-0.2.1.dist-info/WHEEL
heaume_cli-0.2.1.dist-info/METADATA
heaume_cli-0.2.1.dist-info/RECORD
