Metadata-Version: 2.1
Name: heaume-cli
Version: 0.2.1
Summary: The CLI of Heaume.
Author: dylandoamaral
Author-email: do.amaral.dylan@gmail.com
Requires-Python: >=3.7.1,<4
Classifier: Programming Language :: Python :: 3
Classifier: Programming Language :: Python :: 3.8
Classifier: Programming Language :: Python :: 3.9
Requires-Dist: click (>=7.1.2,<8.0.0)
Requires-Dist: influxdb-client (>=1.14.0,<2.0.0)
Requires-Dist: pandas (>=1.2.2,<2.0.0)
Requires-Dist: pendulum (>=2.1.2,<3.0.0)
Requires-Dist: requests (>=2.25.1,<3.0.0)
Requires-Dist: rich (>=9.10.0,<10.0.0)
